Workbook

Sheet Raw_Data
A1: order_id | B1: OrderDate | C1: Customer | D1: region | E1: City | F1: Category | G1: product_name | H1: Qty | I1: Price | J1: Disc | K1: SalesRep | L1: Pay Method | M1: Status
A2: ORD-1001 | B2: 45716 | C2: Fatima Mirza | D2: kpk | E2: Peshawar | F2: Beauty | G2: Hair Dryer | H2: 2 | I2: PKR 4,050 | K2: Nimra Aslam | L2: Cash | M2: completed
A3: ORD-1002 | B3: 11-Nov-2025 | C3: Bilal Qureshi | D3: SINDH | E3: Karachi | F3: Electronics | G3: Bluetooth Speaker | H3: 6 | I3: PKR 4,450 | K3: waqar ahmed | L3: CC | M3: COMPLETE
A4: ORD-1003 | B4: 2025-05-15 | C4: nida siddiqui | D4: Sind | E4: Karachi | F4: Home & Kitchen | G4: HAND BLENDER | H4: 1 | I4: PKR 3,700 | J4: 0 | K4: Zoya Tariq | L4: Debit | M4: Completed
A5: ORD-1004 | B5: 2025-04-12 | C5: Hassan Siddiqui | D5: Sind | E5: Hyderabad | F5: Home&Kitchen | G5: Hand Blender | H5: 3 | I5: 3850 | K5: Faisal Mehmood | L5: credit card | M5: Completed
A6: ORD-1005 | B6: 46014 | C6: Maryam Qureshi | D6: Khyber Pakhtunkhwa | E6: Peshawar | F6: grocery | G6: Refined Sugar 10 Kg | H6: 6 | I6: 1650 | J6: 10% | K6: Nimra Aslam | L6: paypal | M6: COMPLETE
A7: ord-1006 | B7: 2025-02-21 | C7: Hassan Raza | D7: BALOCHISTAN | E7: quetta | F7: BEAUTY | G7: Perfume Spray | H7: 3 | I7: PKR 3,750 | J7: 20% | K7: Faisal Mehmood | L7: PAYPAL | M7: COMPLETE
A8: ORD-1007 | B8: 2025-03-08 | C8: Tariq Siddiqui | D8: Punjab | E8: Gujranwala | F8: home and kitchen | G8: Rice Cooker | H8: 4 | I8: Rs. 7,750 | J8: 0.05 | K8: Imran Shah | L8: Debit | M8: Completed
A9: ORD-1008 | B9: 45810 | C9: ZAIN RAZA | D9: Sindh | E9: Karachi | F9: electronics | G9: Wireless Earbuds | H9: 1 | I9: PKR 6,650 | J9: 0% | K9: Zoya Tariq | L9: Debit Card | M9: completed
A10: ORD-1009 | B10: 45937 | C10: Fatima Mirza | D10: punjab | E10: Lahore | F10: grocery | G10: Black Tea Pack | H10: 4 | I10: 1550 | K10: Sadia Noor | L10: Credit Card | M10: RETURNED
A11: ORD-1010 | B11: 05-Apr-2025 | C11: SANA RAZA | D11: Punjab | E11: Faisalabad | F11: Groceries | G11: Refined Sugar 10 Kg | H11: 2 | I11: 1650 | J11: 0 | K11: nimra aslam | L11: cash | M11: Completed
A12: ORD-1011 | B12: 45872 | C12: Hassan Raza | D12: punjab | E12: Lahore | F12: home and kitchen | G12: HAND BLENDER | H12: 3 | I12: 3700 | J12: 0.1 | K12: Zoya Tariq | L12: cash | M12: Completed
A13: ORD-1012 | B13: 08/09/2025 | C13: Ahmed Hussain | D13: PUNJAB | E13: Lahore | F13: Beauty | G13: face wash | H13: 2 | I13: 850.00 | J13: 0 | K13: Faisal Mehmood | L13: Credit Card | M13: Completed
A14: ORD-1013 | B14: 07-Feb-2025 | C14: Hina Chaudhry | D14: KPK | E14: Mardan | F14: HOME & KITCHEN | G14: Rice Cooker | H14: 4 | I14: 7200 | J14: 0 | K14: Sadia Noor | L14: CC | M14: COMPLETE
A15: ORD-1014 | B15: 2025-04-15 | C15: AHMED QURESHI | D15: Sindh | E15: Karachi | G15: Face Wash | H15: 4 | K15: Faisal Mehmood | L15: credit card | M15: Completed
A16: ord-1015 | B16: 45825 | C16: saad iqbal | D16: Punjab | E16: Gujranwala | F16: Groceries | G16: Refined Sugar 10 Kg | H16: 4 | I16: PKR 1,600 | J16: 0.05 | K16: Waqar Ahmed | L16: CC | M16: completed
A17: ORD-1016 | B17: 45880 | C17: Iqra Butt | D17: K.P.K | E17: Peshawar | F17: Electronics | G17: Smart Watch | H17: 4 | I17: 9950 | K17: Imran Shah | L17: CASH | M17: pending
A18: ORD-1017 | B18: 45933 | C18: Hina Qureshi | D18: Pnjab | E18: Lahore | F18: Home & Kitchen | G18: air fryer | H18: 3 | I18: 18600 | J18: 10% | K18: Nimra Aslam | L18: paypal | M18: Completed
A19: ord-1018 | B19: 45719 | C19: Hassan Iqbal | D19: Punjab | E19: multan | F19: GROCERIES | G19: refined sugar 10 kg | H19: 1 | I19: 1600 | K19: zoya tariq | L19: cash | M19: COMPLETE
A20: ORD-1019 | B20: 2025-06-09 | C20: Ahmed Hussain | D20: sindh | E20: Karachi | F20: Clothing | G20: Running Shoes | H20: 2 | I20: PKR 7,550 | K20: NIMRA ASLAM | L20: Debit Card | M20: Cancelled
A21: ORD-1020 | B21: 45726 | C21: fatima qureshi | D21: PUNJAB | E21: Lahore | F21: Clothing | G21: Lawn Suit 3 Piece | H21: 5 | I21: PKR 6,700 | J21: 0.1 | K21: Zoya Tariq | L21: CASH | M21: Cancelled
A22: ORD-1021 | B22: 25/08/2025 | C22: sana sheikh | D22: Khyber Pakhtunkhwa | E22: abbottabad | F22: Home&Kitchen | G22: Rice Cooker | H22: 4 | I22: 7200 | K22: Zoya Tariq | L22: Debit | M22: RETURNED
A23: ORD-1022 | B23: 45920 | C23: Ayesha Sheikh | D23: SINDH | E23: KARACHI | F23: Electronics | G23: Phone Charger | I23: 1200 | J23: 10 | K23: Nimra Aslam | L23: CC | M23: Completed
A24: ORD-1023 | B24: 2025-11-23 | C24: BILAL QURESHI | D24: KPK | E24: peshawar | F24: BEAUTY | G24: Face Wash | H24: 3 | I24: Rs. 850 | J24: 0 | K24: Zoya Tariq | L24: debit card | M24: COMPLETE
A25: ORD-1024 | B25: 45722 | C25: Tariq Qureshi | D25: PUNJAB | E25: Rawalpindi | F25: Clothing | G25: Winter Jacket | H25: 2 | I25: 9800 | J25: 0.1 | K25: Faisal Mehmood | L25: credit card | M25: Completed
A26: ORD-1025 | B26: 45883 | C26: Maryam Raza | D26: Sind | E26: Karachi | F26: Home & Kitchen | G26: Hand Blender | H26: 3 | I26: PKR 3,700 | K26: Sadia Noor | L26: cash | M26: COMPLETE
A27: ORD-1026 | B27: 21-Jan-2025 | C27: Nida Siddiqui | E27: Faisalabad | F27: ELECTRONICS | G27: Phone Charger | H27: 7 | I27: 1250 | K27: Zoya Tariq | L27: Credit Card | M27: completed
A28: ORD-1027 | B28: 20-Nov-2025 | C28: Ahmed Siddiqui | D28: PUNJAB | E28: Lahore | F28: Home & Kitchen | G28: hand blender | H28: 2 | I28: Rs. 3,900 | J28: 0% | K28: Zoya Tariq | L28: Cash | M28: completed
A29: ORD-1028 | B29: 46004 | C29: Fatima Mirza | D29: Pnjab | E29: Lahore | F29: Home&Kitchen | G29: rice cooker | H29: 3 | I29: 7200 | J29: 0 | K29: Zoya Tariq | L29: CREDIT CARD | M29: COMPLETE
A30: ORD-1029 | B30: 45836 | C30: Fatima Hussain | D30: Sindh | E30: Karachi | F30: electronics | G30: SMART WATCH | H30: 3 | I30: 9250 | K30: Nimra Aslam | L30: cash | M30: COMPLETE
A31: ORD-1030 | B31: 45881 | C31: Iqra Ansari | D31: Punjab | E31: Multan | F31: home and kitchen | G31: Bedsheet Set | I31: 5300 | J31: 20% | K31: Sadia Noor | L31: paypal | M31: completed
A32: ord-1031 | B32: 2025-12-03 | C32: ZAIN IQBAL | D32: Pnjab | E32: Faisalabad | F32: electronics | G32: Smart Television 43 Inch | H32: 1 | I32: Rs. 51,800 | K32: Imran Shah | L32: Debit | M32: Completed
A33: ORD-1032 | B33: 28-Aug-2025 | C33: Hina Chaudhry | E33: abbottabad | F33: CLOTHING | G33: Running Shoes | H33: 2 | I33: 8,250.00 | K33: Nimra Aslam | L33: Credit Card | M33: completed
A34: ORD-1033 | B34: 30-Sep-2025 | C34: Saad Iqbal | D34: Baluchistan | E34: Quetta | F34: CLOTHING | G34: lawn suit 3 piece | H34: 2 | I34: PKR 6,750 | J34: 15% | K34: Nimra Aslam | L34: Credit Card | M34: PENDING
A35: ORD-1034 | B35: 24/07/2025 | C35: Sana Raza | D35: kpk | E35: Abbottabad | F35: GROCERIES | G35: Cooking Oil 5 Litre | H35: 3 | I35: 2250 | J35: 0.2 | K35: Zoya Tariq | L35: CC | M35: Completed
A36: ORD-1035 | B36: 45872 | C36: Noor Sheikh | D36: PUNJAB | E36: Lahore | F36: grocery | G36: Cooking Oil 5 Litre | H36: 1 | I36: Rs. 2,350 | J36: 0 | K36: waqar ahmed | L36: debit card | M36: COMPLETE
A37: ORD-1036 | B37: 45919 | C37: Sana Raza | D37: Punjab | E37: gujranwala | F37: Electronics | G37: WIRELESS EARBUDS | I37: PKR 6,350 | J37: 10% | K37: Nimra Aslam | L37: CASH | M37: completed
A38: ORD-1037 | B38: 12-Jul-2025 | C38: Saad Siddiqui | D38: PUNJAB | E38: GUJRANWALA | F38: beauty | G38: FACE WASH | H38: 4 | I38: 850 | K38: Nimra Aslam | L38: CREDIT CARD | M38: COMPLETE
A39: ORD-1038 | B39: 45696 | C39: Usman Raza | D39: PUNJAB | E39: Rawalpindi | F39: grocery | G39: Black Tea Pack | H39: 1 | I39: 1500 | J39: 0.1 | K39: Sadia Noor | L39: Cash | M39: Pending
A40: ORD-1039 | B40: 45989 | C40: Hamza Hussain | D40: PUNJAB | E40: Multan | F40: CLOTHING | G40: lawn suit 3 piece | H40: -4 | I40: 7100 | J40: 20 | K40: Imran Shah | L40: Cash | M40: Completed
A41: ORD-1040 | B41: 2025-01-02 | C41: Bilal Hussain | D41: Punjab | E41: Lahore | F41: Electronics | G41: Bluetooth Speaker | H41: 1 | I41: Rs. 4,300 | J41: 0 | K41: NIMRA ASLAM | L41: PayPal | M41: completed
A42: ORD-1041 | B42: 29-Jun-2025 | C42: Saad Siddiqui | D42: Pnjab | E42: rawalpindi | F42: Electronics | G42: PHONE CHARGER | H42: N/A | I42: Rs. 1,200 | J42: 0.1 | K42: Faisal Mehmood | L42: Cash | M42: Completed
A43: ORD-1042 | B43: 45967 | E43: Rawalpindi | F43: electronics | G43: Bluetooth Speaker | H43: 2 | J43: 15 | K43: Waqar Ahmed | L43: PAYPAL | M43: Completed
A44: ORD-1043 | B44: 2025-08-04 | C44: kashif sheikh | D44: Punjab | E44: Faisalabad | F44: Electronics | G44: SMART WATCH | H44: 3 | I44: 9850 | J44: 0 | K44: Sadia Noor | L44: Debit Card | M44: Completed
A45: ORD-1044 | B45: 45877 | C45: Bilal Hussain | D45: sindh | E45: karachi | F45: Groceries | G45: Cooking Oil 5 Litre | H45: -3 | I45: Rs. 2,300 | J45: 0.1 | K45: Imran Shah | L45: Cash | M45: COMPLETE
A46: ORD-1045 | B46: 2025-06-02 | C46: SANA SHEIKH | D46: Punjab | E46: Rawalpindi | F46: Clothes | G46: LAWN SUIT 3 PIECE | H46: 2 | I46: 6,550.00 | J46: 0.05 | K46: Nimra Aslam | L46: debit card | M46: RETURNED
A47: ORD-1046 | B47: 2025-02-12 | C47: kashif malik | D47: Punjab | E47: Lahore | F47: clothing | G47: Mens Kurta | H47: 5 | I47: 3150 | J47: 10% | K47: Nimra Aslam | L47: CASH | M47: Completed
A48: ORD-1047 | B48: 2025-12-19 | C48: Hamza Malik | D48: kpk | E48: PESHAWAR | F48: electronics | G48: Smart Television 43 Inch | H48: 5 | I48: PKR 51,800 | K48: Imran Shah | L48: Debit Card | M48: completed
A49: ORD-1048 | B49: 45682 | C49: Ali Malik | D49: Sindh | E49: Hyderabad | F49: grocery | G49: Basmati Rice 5 Kg | H49: 3 | I49: Rs. 2,700 | J49: 15 | K49: Imran Shah | L49: PAYPAL | M49: COMPLETE
A50: ORD-1049 | B50: 45864 | C50: Kashif Malik | D50: sindh | E50: Karachi | F50: BEAUTY | G50: Face Wash | H50: 3 | I50: PKR 900 | J50: 0 | K50: Nimra Aslam | L50: CREDIT CARD | M50: completed
A51: ORD-1050 | B51: 02/08/2025 | C51: Noor Sheikh | D51: Punjab | E51: LAHORE | F51: Groceries | G51: refined sugar 10 kg | H51: 2 | I51: 1600 | J51: 10% | K51: Imran Shah | L51: credit card | M51: Completed
A52: Ord-1051 | B52: 2025-02-23 | C52: Zain Raza | D52: Sindh | E52: Karachi | F52: ELECTRONICS | G52: Smart Television 43 Inch | H52: 6 | I52: 51450 | J52: 0% | K52: Sadia Noor | L52: CREDIT CARD | M52: completed
A53: Ord-1052 | B53: 45962 | C53: Rabia Iqbal | D53: Punjab | E53: Multan | F53: Home&Kitchen | G53: Hand Blender | H53: 1 | I53: 3850 | J53: 0% | K53: Sadia Noor | L53: Credit Card | M53: Completed
A54: ORD-1053 | B54: 45787 | C54: ali butt | D54: K.P.K | E54: Peshawar | F54: CLOTHING | G54: Winter Jacket | H54: 4 | I54: 9650 | J54: 5% | K54: Nimra Aslam | L54: CC | M54: Completed
A55: ORD-1054 | B55: 45703 | C55: Kashif Sheikh | D55: punjab | E55: Lahore | F55: ELECTRONICS | G55: Wireless Earbuds | H55: 8 | I55: Rs. 6,750 | J55: 0.2 | K55: Zoya Tariq | L55: paypal | M55: Completed
A56: ORD-1055 | B56: 09-Sep-2025 | C56: USMAN QURESHI | D56: punjab | E56: Lahore | F56: CLOTHING | G56: Winter Jacket | H56: 1 | I56: Rs. 9,700 | K56: Zoya Tariq | L56: debit card | M56: Completed
A57: ORD-1056 | B57: 2025-04-19 | C57: Ahmed Siddiqui | D57: PUNJAB | E57: LAHORE | F57: beauty | G57: Face Wash | H57: 6 | I57: PKR 800 | J57: 0.1 | L57: Credit Card | M57: Completed
A58: ORD-1057 | B58: 45984 | C58: hassan qureshi | D58: PUNJAB | E58: lahore | F58: GROCERIES | G58: Refined Sugar 10 Kg | H58: 3 | I58: Rs. 1,550 | K58: Sadia Noor | L58: CREDIT CARD | M58: CANCELLED
A59: ord-1058 | B59: 2025-09-29 | C59: hina qureshi | D59: Punjab | E59: Faisalabad | F59: Clothes | G59: Mens Kurta | H59: 8 | I59: Rs. 3,200 | J59: 0% | K59: SADIA NOOR | L59: debit card | M59: completed
A60: ORD-1059 | B60: 20/04/2025 | C60: Hassan Butt | D60: sindh | E60: SUKKUR | F60: GROCERIES | G60: Refined Sugar 10 Kg | H60: 2 | I60: 1700 | K60: faisal mehmood | L60: paypal | M60: COMPLETE
A61: ORD-1060 | B61: 45703 | C61: Sana Raza | D61: PUNJAB | E61: Lahore | F61: beauty | G61: Hair Dryer | H61: 5 | I61: 4300 | J61: 20% | K61: Waqar Ahmed | L61: Debit Card | M61: Cancelled
A62: ORD-1061 | B62: 2025-06-18 | C62: Fatima Mirza | D62: Punjab | E62: Rawalpindi | G62: air fryer | H62: 2 | I62: 18400 | J62: 0 | K62: sadia noor | L62: PayPal | M62: Completed
A63: ORD-1062 | B63: 06-Jul-2025 | C63: Iqra Butt | D63: PUNJAB | E63: Lahore | F63: Home&Kitchen | G63: Hand Blender | H63: 2 | I63: 3,900.00 | K63: Nimra Aslam | L63: CASH | M63: COMPLETE
A64: ORD-1063 | B64: 08/02/2025 | C64: fatima hussain | D64: PUNJAB | E64: Gujranwala | F64: Electronic | G64: SMART TELEVISION 43 INCH | H64: 6 | I64: 52800 | J64: 0 | K64: Faisal Mehmood | L64: Credit Card | M64: COMPLETE
A65: ORD-1064 | B65: 16-Nov-2025 | C65: Zain Iqbal | D65: Punjab | E65: Lahore | F65: Clothes | G65: Mens Kurta | H65: 6 | I65: 3,100.00 | J65: 5% | K65: Zoya Tariq | L65: PayPal | M65: Returned
A66: ORD-1065 | B66: 23-Jul-2025 | C66: Iqra Sheikh | D66: Sindh | E66: Sukkur | F66: Groceries | G66: BLACK TEA PACK | H66: 5 | I66: 1500 | J66: 0% | K66: Waqar Ahmed | L66: Credit Card | M66: Completed
A67: ORD-1066 | B67: 2025-12-22 | C67: OMAR SHEIKH | D67: Sindh | E67: Karachi | F67: Beauty | G67: Perfume Spray | H67: 1 | I67: PKR 3,950 | K67: FAISAL MEHMOOD | L67: DC | M67: Cancelled
A68: ORD-1067 | B68: 45821 | C68: kashif malik | D68: Pnjab | E68: LAHORE | F68: Electronics | G68: Smart Watch | H68: 5 | I68: Rs. 9,500 | J68: 15% | K68: Waqar Ahmed | L68: PAYPAL | M68: Completed
A69: ORD-1068 | B69: 45718 | C69: Sana Raza | D69: Pnjab | E69: Rawalpindi | F69: Home & Kitchen | G69: Bedsheet Set | H69: 1 | I69: 5,250.00 | J69: 5% | K69: Zoya Tariq | L69: Debit Card | M69: Completed
A70: ORD-1069 | B70: 45686 | D70: Sind | E70: Karachi | F70: Clothing | G70: Lawn Suit 3 Piece | H70: 1 | I70: Rs. 6,500 | J70: 0 | K70: zoya tariq | L70: Cash | M70: COMPLETE
A71: ord-1070 | B71: 13/09/2025 | C71: hassan siddiqui | D71: Sind | E71: hyderabad | F71: GROCERIES | G71: Black Tea Pack | H71: two | I71: PKR 1,550 | K71: nimra aslam | L71: CASH | M71: returned
A72: ORD-1071 | B72: 12-Aug-2025 | C72: Tariq Siddiqui | D72: Punjab | E72: Lahore | F72: beauty | G72: face wash | H72: 8 | I72: 850 | J72: 0.05 | K72: Waqar Ahmed | L72: CREDIT CARD | M72: RETURNED
A73: ORD-1072 | B73: 06-Nov-2025 | C73: hina siddiqui | D73: Punjab | E73: Multan | F73: Clothes | G73: Running Shoes | H73: 5 | I73: 7750 | J73: 0 | K73: Nimra Aslam | L73: cash | M73: Cancelled
A74: ORD-1073 | B74: 18-Mar-2025 | C74: Kashif Khan | D74: sindh | E74: Hyderabad | F74: Electronics | G74: wireless earbuds | H74: 2 | I74: Rs. 6,400 | K74: Imran Shah | L74: cash | M74: completed
A75: ORD-1074 | B75: 10/11/2025 | C75: Ayesha Malik | D75: Pnjab | E75: Lahore | F75: clothing | G75: Running Shoes | H75: 3 | I75: 8000 | J75: 0.15 | K75: faisal mehmood | L75: DC | M75: Completed
A76: ORD-1075 | B76: 2025-10-23 | C76: Hina Qureshi | D76: PUNJAB | E76: faisalabad | F76: electronics | G76: smart television 43 inch | H76: 3 | I76: Rs. 52,650 | J76: 10% | K76: Nimra Aslam | L76: CC | M76: completed
A77: Ord-1076 | B77: 27/07/2025 | C77: Ahmed Qureshi | D77: SINDH | E77: Karachi | F77: BEAUTY | G77: Face Wash | H77: 2 | I77: PKR 850 | K77: Sadia Noor | L77: credit card | M77: COMPLETE
A78: ORD-1077 | B78: 2025-12-11 | C78: Sana Raza | D78: Punjab | E78: Multan | F78: Groceries | G78: Black Tea Pack | H78: 2 | I78: PKR 1,450 | J78: 0.05 | K78: Nimra Aslam | L78: CC | M78: Completed
A79: Ord-1078 | B79: 25/12/2025 | C79: Iqra Butt | D79: Punjab | E79: Faisalabad | F79: GROCERIES | G79: Basmati Rice 5 Kg | H79: 6 | I79: 2550 | J79: 0 | K79: Faisal Mehmood | L79: CASH | M79: completed
A80: ORD-1079 | B80: 20-Jan-2025 | C80: Kashif Malik | D80: punjab | E80: multan | F80: BEAUTY | G80: Hair Dryer | H80: 2 | I80: PKR 4,150 | K80: WAQAR AHMED | L80: PAYPAL | M80: COMPLETE
A81: ORD-1080 | B81: 22/09/2025 | C81: Maryam Qureshi | D81: Sindh | E81: Sukkur | F81: clothing | G81: Running Shoes | H81: 2 | I81: 8,000.00 | J81: 0.1 | K81: nimra aslam | L81: Debit Card | M81: completed
A82: ORD-1081 | B82: 17-Oct-2025 | C82: Tariq Khan | D82: sindh | E82: Karachi | F82: grocery | G82: Basmati Rice 5 Kg | H82: 2 | I82: Rs. 2,500 | J82: 0.1 | K82: Imran Shah | L82: CASH | M82: completed
A83: ORD-1082 | B83: 12/02/2025 | C83: Ayesha Siddiqui | D83: Pnjab | E83: multan | F83: CLOTHING | G83: Lawn Suit 3 Piece | H83: 1 | I83: 6500 | J83: 0% | K83: Imran Shah | L83: CREDIT CARD | M83: Completed
A84: Ord-1083 | B84: 45671 | C84: Usman Mirza | D84: Punjab | E84: Gujranwala | F84: ELECTRONICS | G84: Bluetooth Speaker | H84: 5 | I84: 4,650.00 | J84: 0.1 | K84: zoya tariq | L84: Credit Card | M84: canceled
A85: ORD-1084 | B85: 2025-07-15 | C85: KASHIF ANSARI | D85: balochistan | E85: Quetta | F85: clothing | G85: Lawn Suit 3 Piece | H85: 6 | I85: PKR 6,700 | L85: Cash | M85: pending
A86: ORD-1085 | B86: 03-Mar-2025 | C86: Nida Siddiqui | D86: PUNJAB | E86: multan | F86: CLOTHING | G86: winter jacket | H86: 2 | I86: 9900 | J86: 5% | K86: NIMRA ASLAM | L86: Credit Card | M86: COMPLETE
A87: ORD-1086 | B87: 20/10/2025 | C87: usman chaudhry | D87: PUNJAB | E87: Lahore | F87: HOME & KITCHEN | G87: Air Fryer | H87: 3 | I87: 18,900.00 | J87: 0.1 | K87: imran shah | L87: CC | M87: completed
A88: Ord-1087 | B88: 11-Jun-2025 | C88: Iqra Butt | D88: Pnjab | E88: Rawalpindi | F88: grocery | G88: black tea pack | H88: 3 | I88: 1,450.00 | J88: 0.15 | K88: FAISAL MEHMOOD | L88: PAYPAL | M88: PENDING
A89: ORD-1088 | B89: 08/01/2025 | C89: Hamza Malik | D89: Punjab | E89: RAWALPINDI | F89: Groceries | G89: Refined Sugar 10 Kg | H89: 3 | I89: PKR 1,650 | J89: 10% | K89: Faisal Mehmood | L89: CREDIT CARD | M89: Completed
A90: ORD-1089 | B90: 04-Jun-2025 | C90: Rabia Khan | D90: Punjab | E90: MULTAN | F90: Electronics | G90: Smart Television 43 Inch | H90: two | I90: N/A | J90: 20% | K90: SADIA NOOR | L90: credit card | M90: RETURNED
A91: ord-1090 | B91: 2025-10-15 | C91: Iqra Ansari | D91: Punjab | E91: LAHORE | F91: CLOTHING | G91: Winter Jacket | H91: 2 | I91: 9,950.00 | J91: 5% | K91: Waqar Ahmed | L91: credit card | M91: COMPLETE
A92: ORD-1091 | B92: 21/07/2025 | C92: Hina Hussain | D92: PUNJAB | E92: Gujranwala | F92: Electronics | G92: Smart Television 43 Inch | H92: 3 | I92: 50600 | J92: 10% | L92: CREDIT CARD | M92: Completed
A93: ORD-1092 | B93: 08/09/2025 | C93: hassan qureshi | D93: sindh | E93: Sukkur | F93: Groceries | G93: REFINED SUGAR 10 KG | H93: 6 | K93: Faisal Mehmood | L93: CREDIT CARD | M93: Completed
A94: ORD-1093 | B94: 2025-07-03 | C94: bilal hussain | D94: SINDH | E94: Karachi | F94: clothing | G94: Winter Jacket | H94: 3 | I94: PKR 9,600 | J94: 10 | K94: Zoya Tariq | L94: CREDIT CARD | M94: Completed
A95: ORD-1094 | B95: 02-Dec-2025 | C95: Noor Sheikh | D95: punjab | E95: Faisalabad | F95: Clothes | G95: Winter Jacket | H95: 3 | I95: 10100 | J95: 0.1 | K95: Nimra Aslam | L95: PAYPAL | M95: returned
A96: ORD-1095 | B96: 46022 | C96: Fatima Mirza | D96: PUNJAB | E96: Multan | F96: Beauty | G96: Face Wash | H96: 5 | I96: 850 | J96: 0 | K96: WAQAR AHMED | L96: Debit Card | M96: Completed
A97: ORD-1096 | B97: 45912 | C97: Hamza Hussain | D97: PUNJAB | E97: Gujranwala | F97: clothing | G97: Winter Jacket | H97: 1 | I97: PKR 9,900 | J97: 5 | K97: Sadia Noor | L97: cash | M97: COMPLETE
A98: ORD-1097 | B98: 15/03/2025 | C98: Ahmed Hussain | E98: rawalpindi | F98: Electronic | G98: Bluetooth Speaker | H98: 6 | I98: 4550 | J98: 20% | K98: Zoya Tariq | L98: Credit Card | M98: completed
A99: Ord-1098 | B99: 25/06/2025 | C99: Sana Raza | D99: PUNJAB | E99: Lahore | F99: Electronic | G99: Wireless Earbuds | H99: 3 | I99: 6800 | J99: 0.1 | K99: Sadia Noor | L99: PayPal | M99: COMPLETE
A100: Ord-1099 | B100: 45949 | C100: Ayesha Sheikh | D100: Punjab | E100: Rawalpindi | F100: HOME & KITCHEN | G100: Bedsheet Set | H100: 3 | I100: 5,400.00 | K100: Nimra Aslam | L100: CASH | M100: Completed
...

Sheet Clean_Data
A1: Order ID | B1: Order Date | C1: Customer Name | D1: Region | E1: City | F1: Category | G1: Product | H1: Quantity | I1: Unit Price (PKR) | J1: Discount % | K1: Sales Rep | L1: Payment Method | M1: Order Status | N1: Gross Sales (PKR) | O1: Discount Amount (PKR) | P1: Net Revenue (PKR) | Q1: Order Month | R1: Row Status | S1: Issue Note
A2: =UPPER(TRIM(Raw_Data!A2)) -> ORD-1001 | B2: =IFERROR(IF(ISNUMBER(Raw_Data!B2),Raw_Data!B2,IF(ISNUMBER(FIND("/",Raw_Data!B2)),DATE(VALUE(RIGHT(TRIM(Raw_Data!B2),4)),VALUE(MID(TRIM(Raw_Data!B2),4,2)),VALUE(LEFT(TRIM(Raw_Data!B2),2))),IF(MID(TRIM(Raw_Data!B2),5,1)="-",DATE(VALUE(LEFT(TRIM(Raw_Data!B2),4)),VALUE(MID(TRIM(Raw_Data!B2),6,2)),VALUE(RIGHT(TRIM(Raw_Data!B2),2))),DATE(VALUE(RIGHT(TRIM(Raw_Data!B2),4)),MATCH(MID(TRIM(Raw_Data!B2),4,3),{"Jan","Feb","Mar","Apr","May","Jun","Jul","Aug","Sep","Oct","Nov","Dec"},0),VALUE(LEFT(TRIM(Raw_Data!B2),2)))))),"") -> 45716 | C2: =IF(TRIM(Raw_Data!C2)="","Unknown",PROPER(TRIM(Raw_Data!C2))) -> Fatima Mirza | D2: =IFERROR(INDEX({"Punjab","Sindh","KPK","Balochistan"},MATCH(UPPER(LEFT(TRIM(Raw_Data!D2),1)),{"P","S","K","B"},0)),IFERROR(INDEX(Data_Dictionary!$G$4:$G$16,MATCH(E2,Data_Dictionary!$F$4:$F$16,0)),"Unassigned")) -> KPK | E2: =IF(TRIM(Raw_Data!E2)="","Unknown",PROPER(TRIM(Raw_Data!E2))) -> Peshawar | F2: =IFERROR(INDEX({"Electronics","Home & Kitchen","Clothing","Groceries","Beauty"},MATCH(UPPER(LEFT(TRIM(Raw_Data!F2),3)),{"ELE","HOM","CLO","GRO","BEA"},0)),"Uncategorised") -> Beauty | G2: =IF(TRIM(Raw_Data!G2)="","Unknown",PROPER(TRIM(Raw_Data!G2))) -> Hair Dryer | H2: =IFERROR(ABS(VALUE(TRIM(Raw_Data!H2))),"") -> 2 | I2: =IFERROR(VALUE(TRIM(SUBSTITUTE(SUBSTITUTE(SUBSTITUTE(SUBSTITUTE(TRIM(Raw_Data!I2),"PKR",""),"Rs.",""),"Rs",""),",",""))),"") -> 4050 | J2: =IFERROR(IF(TRIM(Raw_Data!J2)="",0,IF(VALUE(TRIM(Raw_Data!J2))>1,VALUE(TRIM(Raw_Data!J2))/100,VALUE(TRIM(Raw_Data!J2)))),0) -> 0 | K2: =IF(TRIM(Raw_Data!K2)="","Unassigned",PROPER(TRIM(Raw_Data!K2))) -> Nimra Aslam | L2: =IFERROR(INDEX({"Credit Card","Credit Card","Debit Card","Debit Card","Cash","PayPal"},MATCH(UPPER(LEFT(TRIM(Raw_Data!L2),2)),{"CR","CC","DE","DC","CA","PA"},0)),"Other") -> Cash | M2: =IFERROR(INDEX({"Completed","Returned","Cancelled","Pending"},MATCH(UPPER(LEFT(TRIM(Raw_Data!M2),3)),{"COM","RET","CAN","PEN"},0)),"Unknown") -> Completed | N2: =IF(OR(H2="",I2=""),"",H2*I2) -> 8100 | O2: =IF(N2="","",N2*J2) -> 0 | P2: =IF(N2="","",N2-O2) -> 8100 | Q2: =IF(B2="","",DATE(YEAR(B2),MONTH(B2),1)) -> 45689 | R2: =IF(A2="","Invalid - Exclude",IF(COUNTIF($A$2:A2,A2)>1,"Duplicate - Exclude",IF(OR(B2="",H2="",I2=""),"Invalid - Exclude","Valid"))) -> Valid | S2: =IF(R2="Valid","",IF(R2="Duplicate - Exclude","Repeat of an earlier Order ID",IF(B2="","Date missing or unreadable",IF(H2="","Quantity missing or unreadable",IF(I2="","Unit price missing or unreadable","Order ID missing")))))
A3: =UPPER(TRIM(Raw_Data!A3)) -> ORD-1002 | B3: =IFERROR(IF(ISNUMBER(Raw_Data!B3),Raw_Data!B3,IF(ISNUMBER(FIND("/",Raw_Data!B3)),DATE(VALUE(RIGHT(TRIM(Raw_Data!B3),4)),VALUE(MID(TRIM(Raw_Data!B3),4,2)),VALUE(LEFT(TRIM(Raw_Data!B3),2))),IF(MID(TRIM(Raw_Data!B3),5,1)="-",DATE(VALUE(LEFT(TRIM(Raw_Data!B3),4)),VALUE(MID(TRIM(Raw_Data!B3),6,2)),VALUE(RIGHT(TRIM(Raw_Data!B3),2))),DATE(VALUE(RIGHT(TRIM(Raw_Data!B3),4)),MATCH(MID(TRIM(Raw_Data!B3),4,3),{"Jan","Feb","Mar","Apr","May","Jun","Jul","Aug","Sep","Oct","Nov","Dec"},0),VALUE(LEFT(TRIM(Raw_Data!B3),2)))))),"") -> 45972 | C3: =IF(TRIM(Raw_Data!C3)="","Unknown",PROPER(TRIM(Raw_Data!C3))) -> Bilal Qureshi | D3: =IFERROR(INDEX({"Punjab","Sindh","KPK","Balochistan"},MATCH(UPPER(LEFT(TRIM(Raw_Data!D3),1)),{"P","S","K","B"},0)),IFERROR(INDEX(Data_Dictionary!$G$4:$G$16,MATCH(E3,Data_Dictionary!$F$4:$F$16,0)),"Unassigned")) -> Sindh | E3: =IF(TRIM(Raw_Data!E3)="","Unknown",PROPER(TRIM(Raw_Data!E3))) -> Karachi | F3: =IFERROR(INDEX({"Electronics","Home & Kitchen","Clothing","Groceries","Beauty"},MATCH(UPPER(LEFT(TRIM(Raw_Data!F3),3)),{"ELE","HOM","CLO","GRO","BEA"},0)),"Uncategorised") -> Electronics | G3: =IF(TRIM(Raw_Data!G3)="","Unknown",PROPER(TRIM(Raw_Data!G3))) -> Bluetooth Speaker | H3: =IFERROR(ABS(VALUE(TRIM(Raw_Data!H3))),"") -> 6 | I3: =IFERROR(VALUE(TRIM(SUBSTITUTE(SUBSTITUTE(SUBSTITUTE(SUBSTITUTE(TRIM(Raw_Data!I3),"PKR",""),"Rs.",""),"Rs",""),",",""))),"") -> 4450 | J3: =IFERROR(IF(TRIM(Raw_Data!J3)="",0,IF(VALUE(TRIM(Raw_Data!J3))>1,VALUE(TRIM(Raw_Data!J3))/100,VALUE(TRIM(Raw_Data!J3)))),0) -> 0 | K3: =IF(TRIM(Raw_Data!K3)="","Unassigned",PROPER(TRIM(Raw_Data!K3))) -> Waqar Ahmed | L3: =IFERROR(INDEX({"Credit Card","Credit Card","Debit Card","Debit Card","Cash","PayPal"},MATCH(UPPER(LEFT(TRIM(Raw_Data!L3),2)),{"CR","CC","DE","DC","CA","PA"},0)),"Other") -> Credit Card | M3: =IFERROR(INDEX({"Completed","Returned","Cancelled","Pending"},MATCH(UPPER(LEFT(TRIM(Raw_Data!M3),3)),{"COM","RET","CAN","PEN"},0)),"Unknown") -> Completed | N3: =IF(OR(H3="",I3=""),"",H3*I3) -> 26700 | O3: =IF(N3="","",N3*J3) -> 0 | P3: =IF(N3="","",N3-O3) -> 26700 | Q3: =IF(B3="","",DATE(YEAR(B3),MONTH(B3),1)) -> 45962 | R3: =IF(A3="","Invalid - Exclude",IF(COUNTIF($A$2:A3,A3)>1,"Duplicate - Exclude",IF(OR(B3="",H3="",I3=""),"Invalid - Exclude","Valid"))) -> Valid | S3: =IF(R3="Valid","",IF(R3="Duplicate - Exclude","Repeat of an earlier Order ID",IF(B3="","Date missing or unreadable",IF(H3="","Quantity missing or unreadable",IF(I3="","Unit price missing or unreadable","Order ID missing")))))
A4: =UPPER(TRIM(Raw_Data!A4)) -> ORD-1003 | B4: =IFERROR(IF(ISNUMBER(Raw_Data!B4),Raw_Data!B4,IF(ISNUMBER(FIND("/",Raw_Data!B4)),DATE(VALUE(RIGHT(TRIM(Raw_Data!B4),4)),VALUE(MID(TRIM(Raw_Data!B4),4,2)),VALUE(LEFT(TRIM(Raw_Data!B4),2))),IF(MID(TRIM(Raw_Data!B4),5,1)="-",DATE(VALUE(LEFT(TRIM(Raw_Data!B4),4)),VALUE(MID(TRIM(Raw_Data!B4),6,2)),VALUE(RIGHT(TRIM(Raw_Data!B4),2))),DATE(VALUE(RIGHT(TRIM(Raw_Data!B4),4)),MATCH(MID(TRIM(Raw_Data!B4),4,3),{"Jan","Feb","Mar","Apr","May","Jun","Jul","Aug","Sep","Oct","Nov","Dec"},0),VALUE(LEFT(TRIM(Raw_Data!B4),2)))))),"") -> 45792 | C4: =IF(TRIM(Raw_Data!C4)="","Unknown",PROPER(TRIM(Raw_Data!C4))) -> Nida Siddiqui | D4: =IFERROR(INDEX({"Punjab","Sindh","KPK","Balochistan"},MATCH(UPPER(LEFT(TRIM(Raw_Data!D4),1)),{"P","S","K","B"},0)),IFERROR(INDEX(Data_Dictionary!$G$4:$G$16,MATCH(E4,Data_Dictionary!$F$4:$F$16,0)),"Unassigned")) -> Sindh | E4: =IF(TRIM(Raw_Data!E4)="","Unknown",PROPER(TRIM(Raw_Data!E4))) -> Karachi | F4: =IFERROR(INDEX({"Electronics","Home & Kitchen","Clothing","Groceries","Beauty"},MATCH(UPPER(LEFT(TRIM(Raw_Data!F4),3)),{"ELE","HOM","CLO","GRO","BEA"},0)),"Uncategorised") -> Home & Kitchen | G4: =IF(TRIM(Raw_Data!G4)="","Unknown",PROPER(TRIM(Raw_Data!G4))) -> Hand Blender | H4: =IFERROR(ABS(VALUE(TRIM(Raw_Data!H4))),"") -> 1 | I4: =IFERROR(VALUE(TRIM(SUBSTITUTE(SUBSTITUTE(SUBSTITUTE(SUBSTITUTE(TRIM(Raw_Data!I4),"PKR",""),"Rs.",""),"Rs",""),",",""))),"") -> 3700 | J4: =IFERROR(IF(TRIM(Raw_Data!J4)="",0,IF(VALUE(TRIM(Raw_Data!J4))>1,VALUE(TRIM(Raw_Data!J4))/100,VALUE(TRIM(Raw_Data!J4)))),0) -> 0 | K4: =IF(TRIM(Raw_Data!K4)="","Unassigned",PROPER(TRIM(Raw_Data!K4))) -> Zoya Tariq | L4: =IFERROR(INDEX({"Credit Card","Credit Card","Debit Card","Debit Card","Cash","PayPal"},MATCH(UPPER(LEFT(TRIM(Raw_Data!L4),2)),{"CR","CC","DE","DC","CA","PA"},0)),"Other") -> Debit Card | M4: =IFERROR(INDEX({"Completed","Returned","Cancelled","Pending"},MATCH(UPPER(LEFT(TRIM(Raw_Data!M4),3)),{"COM","RET","CAN","PEN"},0)),"Unknown") -> Completed | N4: =IF(OR(H4="",I4=""),"",H4*I4) -> 3700 | O4: =IF(N4="","",N4*J4) -> 0 | P4: =IF(N4="","",N4-O4) -> 3700 | Q4: =IF(B4="","",DATE(YEAR(B4),MONTH(B4),1)) -> 45778 | R4: =IF(A4="","Invalid - Exclude",IF(COUNTIF($A$2:A4,A4)>1,"Duplicate - Exclude",IF(OR(B4="",H4="",I4=""),"Invalid - Exclude","Valid"))) -> Valid | S4: =IF(R4="Valid","",IF(R4="Duplicate - Exclude","Repeat of an earlier Order ID",IF(B4="","Date missing or unreadable",IF(H4="","Quantity missing or unreadable",IF(I4="","Unit price missing or unreadable","Order ID missing")))))
A5: =UPPER(TRIM(Raw_Data!A5)) -> ORD-1004 | B5: =IFERROR(IF(ISNUMBER(Raw_Data!B5),Raw_Data!B5,IF(ISNUMBER(FIND("/",Raw_Data!B5)),DATE(VALUE(RIGHT(TRIM(Raw_Data!B5),4)),VALUE(MID(TRIM(Raw_Data!B5),4,2)),VALUE(LEFT(TRIM(Raw_Data!B5),2))),IF(MID(TRIM(Raw_Data!B5),5,1)="-",DATE(VALUE(LEFT(TRIM(Raw_Data!B5),4)),VALUE(MID(TRIM(Raw_Data!B5),6,2)),VALUE(RIGHT(TRIM(Raw_Data!B5),2))),DATE(VALUE(RIGHT(TRIM(Raw_Data!B5),4)),MATCH(MID(TRIM(Raw_Data!B5),4,3),{"Jan","Feb","Mar","Apr","May","Jun","Jul","Aug","Sep","Oct","Nov","Dec"},0),VALUE(LEFT(TRIM(Raw_Data!B5),2)))))),"") -> 45759 | C5: =IF(TRIM(Raw_Data!C5)="","Unknown",PROPER(TRIM(Raw_Data!C5))) -> Hassan Siddiqui | D5: =IFERROR(INDEX({"Punjab","Sindh","KPK","Balochistan"},MATCH(UPPER(LEFT(TRIM(Raw_Data!D5),1)),{"P","S","K","B"},0)),IFERROR(INDEX(Data_Dictionary!$G$4:$G$16,MATCH(E5,Data_Dictionary!$F$4:$F$16,0)),"Unassigned")) -> Sindh | E5: =IF(TRIM(Raw_Data!E5)="","Unknown",PROPER(TRIM(Raw_Data!E5))) -> Hyderabad | F5: =IFERROR(INDEX({"Electronics","Home & Kitchen","Clothing","Groceries","Beauty"},MATCH(UPPER(LEFT(TRIM(Raw_Data!F5),3)),{"ELE","HOM","CLO","GRO","BEA"},0)),"Uncategorised") -> Home & Kitchen | G5: =IF(TRIM(Raw_Data!G5)="","Unknown",PROPER(TRIM(Raw_Data!G5))) -> Hand Blender | H5: =IFERROR(ABS(VALUE(TRIM(Raw_Data!H5))),"") -> 3 | I5: =IFERROR(VALUE(TRIM(SUBSTITUTE(SUBSTITUTE(SUBSTITUTE(SUBSTITUTE(TRIM(Raw_Data!I5),"PKR",""),"Rs.",""),"Rs",""),",",""))),"") -> 3850 | J5: =IFERROR(IF(TRIM(Raw_Data!J5)="",0,IF(VALUE(TRIM(Raw_Data!J5))>1,VALUE(TRIM(Raw_Data!J5))/100,VALUE(TRIM(Raw_Data!J5)))),0) -> 0 | K5: =IF(TRIM(Raw_Data!K5)="","Unassigned",PROPER(TRIM(Raw_Data!K5))) -> Faisal Mehmood | L5: =IFERROR(INDEX({"Credit Card","Credit Card","Debit Card","Debit Card","Cash","PayPal"},MATCH(UPPER(LEFT(TRIM(Raw_Data!L5),2)),{"CR","CC","DE","DC","CA","PA"},0)),"Other") -> Credit Card | M5: =IFERROR(INDEX({"Completed","Returned","Cancelled","Pending"},MATCH(UPPER(LEFT(TRIM(Raw_Data!M5),3)),{"COM","RET","CAN","PEN"},0)),"Unknown") -> Completed | N5: =IF(OR(H5="",I5=""),"",H5*I5) -> 11550 | O5: =IF(N5="","",N5*J5) -> 0 | P5: =IF(N5="","",N5-O5) -> 11550 | Q5: =IF(B5="","",DATE(YEAR(B5),MONTH(B5),1)) -> 45748 | R5: =IF(A5="","Invalid - Exclude",IF(COUNTIF($A$2:A5,A5)>1,"Duplicate - Exclude",IF(OR(B5="",H5="",I5=""),"Invalid - Exclude","Valid"))) -> Valid | S5: =IF(R5="Valid","",IF(R5="Duplicate - Exclude","Repeat of an earlier Order ID",IF(B5="","Date missing or unreadable",IF(H5="","Quantity missing or unreadable",IF(I5="","Unit price missing or unreadable","Order ID missing")))))
A6: =UPPER(TRIM(Raw_Data!A6)) -> ORD-1005 | B6: =IFERROR(IF(ISNUMBER(Raw_Data!B6),Raw_Data!B6,IF(ISNUMBER(FIND("/",Raw_Data!B6)),DATE(VALUE(RIGHT(TRIM(Raw_Data!B6),4)),VALUE(MID(TRIM(Raw_Data!B6),4,2)),VALUE(LEFT(TRIM(Raw_Data!B6),2))),IF(MID(TRIM(Raw_Data!B6),5,1)="-",DATE(VALUE(LEFT(TRIM(Raw_Data!B6),4)),VALUE(MID(TRIM(Raw_Data!B6),6,2)),VALUE(RIGHT(TRIM(Raw_Data!B6),2))),DATE(VALUE(RIGHT(TRIM(Raw_Data!B6),4)),MATCH(MID(TRIM(Raw_Data!B6),4,3),{"Jan","Feb","Mar","Apr","May","Jun","Jul","Aug","Sep","Oct","Nov","Dec"},0),VALUE(LEFT(TRIM(Raw_Data!B6),2)))))),"") -> 46014 | C6: =IF(TRIM(Raw_Data!C6)="","Unknown",PROPER(TRIM(Raw_Data!C6))) -> Maryam Qureshi | D6: =IFERROR(INDEX({"Punjab","Sindh","KPK","Balochistan"},MATCH(UPPER(LEFT(TRIM(Raw_Data!D6),1)),{"P","S","K","B"},0)),IFERROR(INDEX(Data_Dictionary!$G$4:$G$16,MATCH(E6,Data_Dictionary!$F$4:$F$16,0)),"Unassigned")) -> KPK | E6: =IF(TRIM(Raw_Data!E6)="","Unknown",PROPER(TRIM(Raw_Data!E6))) -> Peshawar | F6: =IFERROR(INDEX({"Electronics","Home & Kitchen","Clothing","Groceries","Beauty"},MATCH(UPPER(LEFT(TRIM(Raw_Data!F6),3)),{"ELE","HOM","CLO","GRO","BEA"},0)),"Uncategorised") -> Groceries | G6: =IF(TRIM(Raw_Data!G6)="","Unknown",PROPER(TRIM(Raw_Data!G6))) -> Refined Sugar 10 Kg | H6: =IFERROR(ABS(VALUE(TRIM(Raw_Data!H6))),"") -> 6 | I6: =IFERROR(VALUE(TRIM(SUBSTITUTE(SUBSTITUTE(SUBSTITUTE(SUBSTITUTE(TRIM(Raw_Data!I6),"PKR",""),"Rs.",""),"Rs",""),",",""))),"") -> 1650 | J6: =IFERROR(IF(TRIM(Raw_Data!J6)="",0,IF(VALUE(TRIM(Raw_Data!J6))>1,VALUE(TRIM(Raw_Data!J6))/100,VALUE(TRIM(Raw_Data!J6)))),0) -> 0.1 | K6: =IF(TRIM(Raw_Data!K6)="","Unassigned",PROPER(TRIM(Raw_Data!K6))) -> Nimra Aslam | L6: =IFERROR(INDEX({"Credit Card","Credit Card","Debit Card","Debit Card","Cash","PayPal"},MATCH(UPPER(LEFT(TRIM(Raw_Data!L6),2)),{"CR","CC","DE","DC","CA","PA"},0)),"Other") -> PayPal | M6: =IFERROR(INDEX({"Completed","Returned","Cancelled","Pending"},MATCH(UPPER(LEFT(TRIM(Raw_Data!M6),3)),{"COM","RET","CAN","PEN"},0)),"Unknown") -> Completed | N6: =IF(OR(H6="",I6=""),"",H6*I6) -> 9900 | O6: =IF(N6="","",N6*J6) -> 990 | P6: =IF(N6="","",N6-O6) -> 8910 | Q6: =IF(B6="","",DATE(YEAR(B6),MONTH(B6),1)) -> 45992 | R6: =IF(A6="","Invalid - Exclude",IF(COUNTIF($A$2:A6,A6)>1,"Duplicate - Exclude",IF(OR(B6="",H6="",I6=""),"Invalid - Exclude","Valid"))) -> Valid | S6: =IF(R6="Valid","",IF(R6="Duplicate - Exclude","Repeat of an earlier Order ID",IF(B6="","Date missing or unreadable",IF(H6="","Quantity missing or unreadable",IF(I6="","Unit price missing or unreadable","Order ID missing")))))
A7: =UPPER(TRIM(Raw_Data!A7)) -> ORD-1006 | B7: =IFERROR(IF(ISNUMBER(Raw_Data!B7),Raw_Data!B7,IF(ISNUMBER(FIND("/",Raw_Data!B7)),DATE(VALUE(RIGHT(TRIM(Raw_Data!B7),4)),VALUE(MID(TRIM(Raw_Data!B7),4,2)),VALUE(LEFT(TRIM(Raw_Data!B7),2))),IF(MID(TRIM(Raw_Data!B7),5,1)="-",DATE(VALUE(LEFT(TRIM(Raw_Data!B7),4)),VALUE(MID(TRIM(Raw_Data!B7),6,2)),VALUE(RIGHT(TRIM(Raw_Data!B7),2))),DATE(VALUE(RIGHT(TRIM(Raw_Data!B7),4)),MATCH(MID(TRIM(Raw_Data!B7),4,3),{"Jan","Feb","Mar","Apr","May","Jun","Jul","Aug","Sep","Oct","Nov","Dec"},0),VALUE(LEFT(TRIM(Raw_Data!B7),2)))))),"") -> 45709 | C7: =IF(TRIM(Raw_Data!C7)="","Unknown",PROPER(TRIM(Raw_Data!C7))) -> Hassan Raza | D7: =IFERROR(INDEX({"Punjab","Sindh","KPK","Balochistan"},MATCH(UPPER(LEFT(TRIM(Raw_Data!D7),1)),{"P","S","K","B"},0)),IFERROR(INDEX(Data_Dictionary!$G$4:$G$16,MATCH(E7,Data_Dictionary!$F$4:$F$16,0)),"Unassigned")) -> Balochistan | E7: =IF(TRIM(Raw_Data!E7)="","Unknown",PROPER(TRIM(Raw_Data!E7))) -> Quetta | F7: =IFERROR(INDEX({"Electronics","Home & Kitchen","Clothing","Groceries","Beauty"},MATCH(UPPER(LEFT(TRIM(Raw_Data!F7),3)),{"ELE","HOM","CLO","GRO","BEA"},0)),"Uncategorised") -> Beauty | G7: =IF(TRIM(Raw_Data!G7)="","Unknown",PROPER(TRIM(Raw_Data!G7))) -> Perfume Spray | H7: =IFERROR(ABS(VALUE(TRIM(Raw_Data!H7))),"") -> 3 | I7: =IFERROR(VALUE(TRIM(SUBSTITUTE(SUBSTITUTE(SUBSTITUTE(SUBSTITUTE(TRIM(Raw_Data!I7),"PKR",""),"Rs.",""),"Rs",""),",",""))),"") -> 3750 | J7: =IFERROR(IF(TRIM(Raw_Data!J7)="",0,IF(VALUE(TRIM(Raw_Data!J7))>1,VALUE(TRIM(Raw_Data!J7))/100,VALUE(TRIM(Raw_Data!J7)))),0) -> 0.2 | K7: =IF(TRIM(Raw_Data!K7)="","Unassigned",PROPER(TRIM(Raw_Data!K7))) -> Faisal Mehmood | L7: =IFERROR(INDEX({"Credit Card","Credit Card","Debit Card","Debit Card","Cash","PayPal"},MATCH(UPPER(LEFT(TRIM(Raw_Data!L7),2)),{"CR","CC","DE","DC","CA","PA"},0)),"Other") -> PayPal | M7: =IFERROR(INDEX({"Completed","Returned","Cancelled","Pending"},MATCH(UPPER(LEFT(TRIM(Raw_Data!M7),3)),{"COM","RET","CAN","PEN"},0)),"Unknown") -> Completed | N7: =IF(OR(H7="",I7=""),"",H7*I7) -> 11250 | O7: =IF(N7="","",N7*J7) -> 2250 | P7: =IF(N7="","",N7-O7) -> 9000 | Q7: =IF(B7="","",DATE(YEAR(B7),MONTH(B7),1)) -> 45689 | R7: =IF(A7="","Invalid - Exclude",IF(COUNTIF($A$2:A7,A7)>1,"Duplicate - Exclude",IF(OR(B7="",H7="",I7=""),"Invalid - Exclude","Valid"))) -> Valid | S7: =IF(R7="Valid","",IF(R7="Duplicate - Exclude","Repeat of an earlier Order ID",IF(B7="","Date missing or unreadable",IF(H7="","Quantity missing or unreadable",IF(I7="","Unit price missing or unreadable","Order ID missing")))))
A8: =UPPER(TRIM(Raw_Data!A8)) -> ORD-1007 | B8: =IFERROR(IF(ISNUMBER(Raw_Data!B8),Raw_Data!B8,IF(ISNUMBER(FIND("/",Raw_Data!B8)),DATE(VALUE(RIGHT(TRIM(Raw_Data!B8),4)),VALUE(MID(TRIM(Raw_Data!B8),4,2)),VALUE(LEFT(TRIM(Raw_Data!B8),2))),IF(MID(TRIM(Raw_Data!B8),5,1)="-",DATE(VALUE(LEFT(TRIM(Raw_Data!B8),4)),VALUE(MID(TRIM(Raw_Data!B8),6,2)),VALUE(RIGHT(TRIM(Raw_Data!B8),2))),DATE(VALUE(RIGHT(TRIM(Raw_Data!B8),4)),MATCH(MID(TRIM(Raw_Data!B8),4,3),{"Jan","Feb","Mar","Apr","May","Jun","Jul","Aug","Sep","Oct","Nov","Dec"},0),VALUE(LEFT(TRIM(Raw_Data!B8),2)))))),"") -> 45724 | C8: =IF(TRIM(Raw_Data!C8)="","Unknown",PROPER(TRIM(Raw_Data!C8))) -> Tariq Siddiqui | D8: =IFERROR(INDEX({"Punjab","Sindh","KPK","Balochistan"},MATCH(UPPER(LEFT(TRIM(Raw_Data!D8),1)),{"P","S","K","B"},0)),IFERROR(INDEX(Data_Dictionary!$G$4:$G$16,MATCH(E8,Data_Dictionary!$F$4:$F$16,0)),"Unassigned")) -> Punjab | E8: =IF(TRIM(Raw_Data!E8)="","Unknown",PROPER(TRIM(Raw_Data!E8))) -> Gujranwala | F8: =IFERROR(INDEX({"Electronics","Home & Kitchen","Clothing","Groceries","Beauty"},MATCH(UPPER(LEFT(TRIM(Raw_Data!F8),3)),{"ELE","HOM","CLO","GRO","BEA"},0)),"Uncategorised") -> Home & Kitchen | G8: =IF(TRIM(Raw_Data!G8)="","Unknown",PROPER(TRIM(Raw_Data!G8))) -> Rice Cooker | H8: =IFERROR(ABS(VALUE(TRIM(Raw_Data!H8))),"") -> 4 | I8: =IFERROR(VALUE(TRIM(SUBSTITUTE(SUBSTITUTE(SUBSTITUTE(SUBSTITUTE(TRIM(Raw_Data!I8),"PKR",""),"Rs.",""),"Rs",""),",",""))),"") -> 7750 | J8: =IFERROR(IF(TRIM(Raw_Data!J8)="",0,IF(VALUE(TRIM(Raw_Data!J8))>1,VALUE(TRIM(Raw_Data!J8))/100,VALUE(TRIM(Raw_Data!J8)))),0) -> 0.05 | K8: =IF(TRIM(Raw_Data!K8)="","Unassigned",PROPER(TRIM(Raw_Data!K8))) -> Imran Shah | L8: =IFERROR(INDEX({"Credit Card","Credit Card","Debit Card","Debit Card","Cash","PayPal"},MATCH(UPPER(LEFT(TRIM(Raw_Data!L8),2)),{"CR","CC","DE","DC","CA","PA"},0)),"Other") -> Debit Card | M8: =IFERROR(INDEX({"Completed","Returned","Cancelled","Pending"},MATCH(UPPER(LEFT(TRIM(Raw_Data!M8),3)),{"COM","RET","CAN","PEN"},0)),"Unknown") -> Completed | N8: =IF(OR(H8="",I8=""),"",H8*I8) -> 31000 | O8: =IF(N8="","",N8*J8) -> 1550 | P8: =IF(N8="","",N8-O8) -> 29450 | Q8: =IF(B8="","",DATE(YEAR(B8),MONTH(B8),1)) -> 45717 | R8: =IF(A8="","Invalid - Exclude",IF(COUNTIF($A$2:A8,A8)>1,"Duplicate - Exclude",IF(OR(B8="",H8="",I8=""),"Invalid - Exclude","Valid"))) -> Valid | S8: =IF(R8="Valid","",IF(R8="Duplicate - Exclude","Repeat of an earlier Order ID",IF(B8="","Date missing or unreadable",IF(H8="","Quantity missing or unreadable",IF(I8="","Unit price missing or unreadable","Order ID missing")))))
A9: =UPPER(TRIM(Raw_Data!A9)) -> ORD-1008 | B9: =IFERROR(IF(ISNUMBER(Raw_Data!B9),Raw_Data!B9,IF(ISNUMBER(FIND("/",Raw_Data!B9)),DATE(VALUE(RIGHT(TRIM(Raw_Data!B9),4)),VALUE(MID(TRIM(Raw_Data!B9),4,2)),VALUE(LEFT(TRIM(Raw_Data!B9),2))),IF(MID(TRIM(Raw_Data!B9),5,1)="-",DATE(VALUE(LEFT(TRIM(Raw_Data!B9),4)),VALUE(MID(TRIM(Raw_Data!B9),6,2)),VALUE(RIGHT(TRIM(Raw_Data!B9),2))),DATE(VALUE(RIGHT(TRIM(Raw_Data!B9),4)),MATCH(MID(TRIM(Raw_Data!B9),4,3),{"Jan","Feb","Mar","Apr","May","Jun","Jul","Aug","Sep","Oct","Nov","Dec"},0),VALUE(LEFT(TRIM(Raw_Data!B9),2)))))),"") -> 45810 | C9: =IF(TRIM(Raw_Data!C9)="","Unknown",PROPER(TRIM(Raw_Data!C9))) -> Zain Raza | D9: =IFERROR(INDEX({"Punjab","Sindh","KPK","Balochistan"},MATCH(UPPER(LEFT(TRIM(Raw_Data!D9),1)),{"P","S","K","B"},0)),IFERROR(INDEX(Data_Dictionary!$G$4:$G$16,MATCH(E9,Data_Dictionary!$F$4:$F$16,0)),"Unassigned")) -> Sindh | E9: =IF(TRIM(Raw_Data!E9)="","Unknown",PROPER(TRIM(Raw_Data!E9))) -> Karachi | F9: =IFERROR(INDEX({"Electronics","Home & Kitchen","Clothing","Groceries","Beauty"},MATCH(UPPER(LEFT(TRIM(Raw_Data!F9),3)),{"ELE","HOM","CLO","GRO","BEA"},0)),"Uncategorised") -> Electronics | G9: =IF(TRIM(Raw_Data!G9)="","Unknown",PROPER(TRIM(Raw_Data!G9))) -> Wireless Earbuds | H9: =IFERROR(ABS(VALUE(TRIM(Raw_Data!H9))),"") -> 1 | I9: =IFERROR(VALUE(TRIM(SUBSTITUTE(SUBSTITUTE(SUBSTITUTE(SUBSTITUTE(TRIM(Raw_Data!I9),"PKR",""),"Rs.",""),"Rs",""),",",""))),"") -> 6650 | J9: =IFERROR(IF(TRIM(Raw_Data!J9)="",0,IF(VALUE(TRIM(Raw_Data!J9))>1,VALUE(TRIM(Raw_Data!J9))/100,VALUE(TRIM(Raw_Data!J9)))),0) -> 0 | K9: =IF(TRIM(Raw_Data!K9)="","Unassigned",PROPER(TRIM(Raw_Data!K9))) -> Zoya Tariq | L9: =IFERROR(INDEX({"Credit Card","Credit Card","Debit Card","Debit Card","Cash","PayPal"},MATCH(UPPER(LEFT(TRIM(Raw_Data!L9),2)),{"CR","CC","DE","DC","CA","PA"},0)),"Other") -> Debit Card | M9: =IFERROR(INDEX({"Completed","Returned","Cancelled","Pending"},MATCH(UPPER(LEFT(TRIM(Raw_Data!M9),3)),{"COM","RET","CAN","PEN"},0)),"Unknown") -> Completed | N9: =IF(OR(H9="",I9=""),"",H9*I9) -> 6650 | O9: =IF(N9="","",N9*J9) -> 0 | P9: =IF(N9="","",N9-O9) -> 6650 | Q9: =IF(B9="","",DATE(YEAR(B9),MONTH(B9),1)) -> 45809 | R9: =IF(A9="","Invalid - Exclude",IF(COUNTIF($A$2:A9,A9)>1,"Duplicate - Exclude",IF(OR(B9="",H9="",I9=""),"Invalid - Exclude","Valid"))) -> Valid | S9: =IF(R9="Valid","",IF(R9="Duplicate - Exclude","Repeat of an earlier Order ID",IF(B9="","Date missing or unreadable",IF(H9="","Quantity missing or unreadable",IF(I9="","Unit price missing or unreadable","Order ID missing")))))
A10: =UPPER(TRIM(Raw_Data!A10)) -> ORD-1009 | B10: =IFERROR(IF(ISNUMBER(Raw_Data!B10),Raw_Data!B10,IF(ISNUMBER(FIND("/",Raw_Data!B10)),DATE(VALUE(RIGHT(TRIM(Raw_Data!B10),4)),VALUE(MID(TRIM(Raw_Data!B10),4,2)),VALUE(LEFT(TRIM(Raw_Data!B10),2))),IF(MID(TRIM(Raw_Data!B10),5,1)="-",DATE(VALUE(LEFT(TRIM(Raw_Data!B10),4)),VALUE(MID(TRIM(Raw_Data!B10),6,2)),VALUE(RIGHT(TRIM(Raw_Data!B10),2))),DATE(VALUE(RIGHT(TRIM(Raw_Data!B10),4)),MATCH(MID(TRIM(Raw_Data!B10),4,3),{"Jan","Feb","Mar","Apr","May","Jun","Jul","Aug","Sep","Oct","Nov","Dec"},0),VALUE(LEFT(TRIM(Raw_Data!B10),2)))))),"") -> 45937 | C10: =IF(TRIM(Raw_Data!C10)="","Unknown",PROPER(TRIM(Raw_Data!C10))) -> Fatima Mirza | D10: =IFERROR(INDEX({"Punjab","Sindh","KPK","Balochistan"},MATCH(UPPER(LEFT(TRIM(Raw_Data!D10),1)),{"P","S","K","B"},0)),IFERROR(INDEX(Data_Dictionary!$G$4:$G$16,MATCH(E10,Data_Dictionary!$F$4:$F$16,0)),"Unassigned")) -> Punjab | E10: =IF(TRIM(Raw_Data!E10)="","Unknown",PROPER(TRIM(Raw_Data!E10))) -> Lahore | F10: =IFERROR(INDEX({"Electronics","Home & Kitchen","Clothing","Groceries","Beauty"},MATCH(UPPER(LEFT(TRIM(Raw_Data!F10),3)),{"ELE","HOM","CLO","GRO","BEA"},0)),"Uncategorised") -> Groceries | G10: =IF(TRIM(Raw_Data!G10)="","Unknown",PROPER(TRIM(Raw_Data!G10))) -> Black Tea Pack | H10: =IFERROR(ABS(VALUE(TRIM(Raw_Data!H10))),"") -> 4 | I10: =IFERROR(VALUE(TRIM(SUBSTITUTE(SUBSTITUTE(SUBSTITUTE(SUBSTITUTE(TRIM(Raw_Data!I10),"PKR",""),"Rs.",""),"Rs",""),",",""))),"") -> 1550 | J10: =IFERROR(IF(TRIM(Raw_Data!J10)="",0,IF(VALUE(TRIM(Raw_Data!J10))>1,VALUE(TRIM(Raw_Data!J10))/100,VALUE(TRIM(Raw_Data!J10)))),0) -> 0 | K10: =IF(TRIM(Raw_Data!K10)="","Unassigned",PROPER(TRIM(Raw_Data!K10))) -> Sadia Noor | L10: =IFERROR(INDEX({"Credit Card","Credit Card","Debit Card","Debit Card","Cash","PayPal"},MATCH(UPPER(LEFT(TRIM(Raw_Data!L10),2)),{"CR","CC","DE","DC","CA","PA"},0)),"Other") -> Credit Card | M10: =IFERROR(INDEX({"Completed","Returned","Cancelled","Pending"},MATCH(UPPER(LEFT(TRIM(Raw_Data!M10),3)),{"COM","RET","CAN","PEN"},0)),"Unknown") -> Returned | N10: =IF(OR(H10="",I10=""),"",H10*I10) -> 6200 | O10: =IF(N10="","",N10*J10) -> 0 | P10: =IF(N10="","",N10-O10) -> 6200 | Q10: =IF(B10="","",DATE(YEAR(B10),MONTH(B10),1)) -> 45931 | R10: =IF(A10="","Invalid - Exclude",IF(COUNTIF($A$2:A10,A10)>1,"Duplicate - Exclude",IF(OR(B10="",H10="",I10=""),"Invalid - Exclude","Valid"))) -> Valid | S10: =IF(R10="Valid","",IF(R10="Duplicate - Exclude","Repeat of an earlier Order ID",IF(B10="","Date missing or unreadable",IF(H10="","Quantity missing or unreadable",IF(I10="","Unit price missing or unreadable","Order ID missing")))))
A11: =UPPER(TRIM(Raw_Data!A11)) -> ORD-1010 | B11: =IFERROR(IF(ISNUMBER(Raw_Data!B11),Raw_Data!B11,IF(ISNUMBER(FIND("/",Raw_Data!B11)),DATE(VALUE(RIGHT(TRIM(Raw_Data!B11),4)),VALUE(MID(TRIM(Raw_Data!B11),4,2)),VALUE(LEFT(TRIM(Raw_Data!B11),2))),IF(MID(TRIM(Raw_Data!B11),5,1)="-",DATE(VALUE(LEFT(TRIM(Raw_Data!B11),4)),VALUE(MID(TRIM(Raw_Data!B11),6,2)),VALUE(RIGHT(TRIM(Raw_Data!B11),2))),DATE(VALUE(RIGHT(TRIM(Raw_Data!B11),4)),MATCH(MID(TRIM(Raw_Data!B11),4,3),{"Jan","Feb","Mar","Apr","May","Jun","Jul","Aug","Sep","Oct","Nov","Dec"},0),VALUE(LEFT(TRIM(Raw_Data!B11),2)))))),"") -> 45752 | C11: =IF(TRIM(Raw_Data!C11)="","Unknown",PROPER(TRIM(Raw_Data!C11))) -> Sana Raza | D11: =IFERROR(INDEX({"Punjab","Sindh","KPK","Balochistan"},MATCH(UPPER(LEFT(TRIM(Raw_Data!D11),1)),{"P","S","K","B"},0)),IFERROR(INDEX(Data_Dictionary!$G$4:$G$16,MATCH(E11,Data_Dictionary!$F$4:$F$16,0)),"Unassigned")) -> Punjab | E11: =IF(TRIM(Raw_Data!E11)="","Unknown",PROPER(TRIM(Raw_Data!E11))) -> Faisalabad | F11: =IFERROR(INDEX({"Electronics","Home & Kitchen","Clothing","Groceries","Beauty"},MATCH(UPPER(LEFT(TRIM(Raw_Data!F11),3)),{"ELE","HOM","CLO","GRO","BEA"},0)),"Uncategorised") -> Groceries | G11: =IF(TRIM(Raw_Data!G11)="","Unknown",PROPER(TRIM(Raw_Data!G11))) -> Refined Sugar 10 Kg | H11: =IFERROR(ABS(VALUE(TRIM(Raw_Data!H11))),"") -> 2 | I11: =IFERROR(VALUE(TRIM(SUBSTITUTE(SUBSTITUTE(SUBSTITUTE(SUBSTITUTE(TRIM(Raw_Data!I11),"PKR",""),"Rs.",""),"Rs",""),",",""))),"") -> 1650 | J11: =IFERROR(IF(TRIM(Raw_Data!J11)="",0,IF(VALUE(TRIM(Raw_Data!J11))>1,VALUE(TRIM(Raw_Data!J11))/100,VALUE(TRIM(Raw_Data!J11)))),0) -> 0 | K11: =IF(TRIM(Raw_Data!K11)="","Unassigned",PROPER(TRIM(Raw_Data!K11))) -> Nimra Aslam | L11: =IFERROR(INDEX({"Credit Card","Credit Card","Debit Card","Debit Card","Cash","PayPal"},MATCH(UPPER(LEFT(TRIM(Raw_Data!L11),2)),{"CR","CC","DE","DC","CA","PA"},0)),"Other") -> Cash | M11: =IFERROR(INDEX({"Completed","Returned","Cancelled","Pending"},MATCH(UPPER(LEFT(TRIM(Raw_Data!M11),3)),{"COM","RET","CAN","PEN"},0)),"Unknown") -> Completed | N11: =IF(OR(H11="",I11=""),"",H11*I11) -> 3300 | O11: =IF(N11="","",N11*J11) -> 0 | P11: =IF(N11="","",N11-O11) -> 3300 | Q11: =IF(B11="","",DATE(YEAR(B11),MONTH(B11),1)) -> 45748 | R11: =IF(A11="","Invalid - Exclude",IF(COUNTIF($A$2:A11,A11)>1,"Duplicate - Exclude",IF(OR(B11="",H11="",I11=""),"Invalid - Exclude","Valid"))) -> Valid | S11: =IF(R11="Valid","",IF(R11="Duplicate - Exclude","Repeat of an earlier Order ID",IF(B11="","Date missing or unreadable",IF(H11="","Quantity missing or unreadable",IF(I11="","Unit price missing or unreadable","Order ID missing")))))
A12: =UPPER(TRIM(Raw_Data!A12)) -> ORD-1011 | B12: =IFERROR(IF(ISNUMBER(Raw_Data!B12),Raw_Data!B12,IF(ISNUMBER(FIND("/",Raw_Data!B12)),DATE(VALUE(RIGHT(TRIM(Raw_Data!B12),4)),VALUE(MID(TRIM(Raw_Data!B12),4,2)),VALUE(LEFT(TRIM(Raw_Data!B12),2))),IF(MID(TRIM(Raw_Data!B12),5,1)="-",DATE(VALUE(LEFT(TRIM(Raw_Data!B12),4)),VALUE(MID(TRIM(Raw_Data!B12),6,2)),VALUE(RIGHT(TRIM(Raw_Data!B12),2))),DATE(VALUE(RIGHT(TRIM(Raw_Data!B12),4)),MATCH(MID(TRIM(Raw_Data!B12),4,3),{"Jan","Feb","Mar","Apr","May","Jun","Jul","Aug","Sep","Oct","Nov","Dec"},0),VALUE(LEFT(TRIM(Raw_Data!B12),2)))))),"") -> 45872 | C12: =IF(TRIM(Raw_Data!C12)="","Unknown",PROPER(TRIM(Raw_Data!C12))) -> Hassan Raza | D12: =IFERROR(INDEX({"Punjab","Sindh","KPK","Balochistan"},MATCH(UPPER(LEFT(TRIM(Raw_Data!D12),1)),{"P","S","K","B"},0)),IFERROR(INDEX(Data_Dictionary!$G$4:$G$16,MATCH(E12,Data_Dictionary!$F$4:$F$16,0)),"Unassigned")) -> Punjab | E12: =IF(TRIM(Raw_Data!E12)="","Unknown",PROPER(TRIM(Raw_Data!E12))) -> Lahore | F12: =IFERROR(INDEX({"Electronics","Home & Kitchen","Clothing","Groceries","Beauty"},MATCH(UPPER(LEFT(TRIM(Raw_Data!F12),3)),{"ELE","HOM","CLO","GRO","BEA"},0)),"Uncategorised") -> Home & Kitchen | G12: =IF(TRIM(Raw_Data!G12)="","Unknown",PROPER(TRIM(Raw_Data!G12))) -> Hand Blender | H12: =IFERROR(ABS(VALUE(TRIM(Raw_Data!H12))),"") -> 3 | I12: =IFERROR(VALUE(TRIM(SUBSTITUTE(SUBSTITUTE(SUBSTITUTE(SUBSTITUTE(TRIM(Raw_Data!I12),"PKR",""),"Rs.",""),"Rs",""),",",""))),"") -> 3700 | J12: =IFERROR(IF(TRIM(Raw_Data!J12)="",0,IF(VALUE(TRIM(Raw_Data!J12))>1,VALUE(TRIM(Raw_Data!J12))/100,VALUE(TRIM(Raw_Data!J12)))),0) -> 0.1 | K12: =IF(TRIM(Raw_Data!K12)="","Unassigned",PROPER(TRIM(Raw_Data!K12))) -> Zoya Tariq | L12: =IFERROR(INDEX({"Credit Card","Credit Card","Debit Card","Debit Card","Cash","PayPal"},MATCH(UPPER(LEFT(TRIM(Raw_Data!L12),2)),{"CR","CC","DE","DC","CA","PA"},0)),"Other") -> Cash | M12: =IFERROR(INDEX({"Completed","Returned","Cancelled","Pending"},MATCH(UPPER(LEFT(TRIM(Raw_Data!M12),3)),{"COM","RET","CAN","PEN"},0)),"Unknown") -> Completed | N12: =IF(OR(H12="",I12=""),"",H12*I12) -> 11100 | O12: =IF(N12="","",N12*J12) -> 1110 | P12: =IF(N12="","",N12-O12) -> 9990 | Q12: =IF(B12="","",DATE(YEAR(B12),MONTH(B12),1)) -> 45870 | R12: =IF(A12="","Invalid - Exclude",IF(COUNTIF($A$2:A12,A12)>1,"Duplicate - Exclude",IF(OR(B12="",H12="",I12=""),"Invalid - Exclude","Valid"))) -> Valid | S12: =IF(R12="Valid","",IF(R12="Duplicate - Exclude","Repeat of an earlier Order ID",IF(B12="","Date missing or unreadable",IF(H12="","Quantity missing or unreadable",IF(I12="","Unit price missing or unreadable","Order ID missing")))))
A13: =UPPER(TRIM(Raw_Data!A13)) -> ORD-1012 | B13: =IFERROR(IF(ISNUMBER(Raw_Data!B13),Raw_Data!B13,IF(ISNUMBER(FIND("/",Raw_Data!B13)),DATE(VALUE(RIGHT(TRIM(Raw_Data!B13),4)),VALUE(MID(TRIM(Raw_Data!B13),4,2)),VALUE(LEFT(TRIM(Raw_Data!B13),2))),IF(MID(TRIM(Raw_Data!B13),5,1)="-",DATE(VALUE(LEFT(TRIM(Raw_Data!B13),4)),VALUE(MID(TRIM(Raw_Data!B13),6,2)),VALUE(RIGHT(TRIM(Raw_Data!B13),2))),DATE(VALUE(RIGHT(TRIM(Raw_Data!B13),4)),MATCH(MID(TRIM(Raw_Data!B13),4,3),{"Jan","Feb","Mar","Apr","May","Jun","Jul","Aug","Sep","Oct","Nov","Dec"},0),VALUE(LEFT(TRIM(Raw_Data!B13),2)))))),"") -> 45908 | C13: =IF(TRIM(Raw_Data!C13)="","Unknown",PROPER(TRIM(Raw_Data!C13))) -> Ahmed Hussain | D13: =IFERROR(INDEX({"Punjab","Sindh","KPK","Balochistan"},MATCH(UPPER(LEFT(TRIM(Raw_Data!D13),1)),{"P","S","K","B"},0)),IFERROR(INDEX(Data_Dictionary!$G$4:$G$16,MATCH(E13,Data_Dictionary!$F$4:$F$16,0)),"Unassigned")) -> Punjab | E13: =IF(TRIM(Raw_Data!E13)="","Unknown",PROPER(TRIM(Raw_Data!E13))) -> Lahore | F13: =IFERROR(INDEX({"Electronics","Home & Kitchen","Clothing","Groceries","Beauty"},MATCH(UPPER(LEFT(TRIM(Raw_Data!F13),3)),{"ELE","HOM","CLO","GRO","BEA"},0)),"Uncategorised") -> Beauty | G13: =IF(TRIM(Raw_Data!G13)="","Unknown",PROPER(TRIM(Raw_Data!G13))) -> Face Wash | H13: =IFERROR(ABS(VALUE(TRIM(Raw_Data!H13))),"") -> 2 | I13: =IFERROR(VALUE(TRIM(SUBSTITUTE(SUBSTITUTE(SUBSTITUTE(SUBSTITUTE(TRIM(Raw_Data!I13),"PKR",""),"Rs.",""),"Rs",""),",",""))),"") -> 850 | J13: =IFERROR(IF(TRIM(Raw_Data!J13)="",0,IF(VALUE(TRIM(Raw_Data!J13))>1,VALUE(TRIM(Raw_Data!J13))/100,VALUE(TRIM(Raw_Data!J13)))),0) -> 0 | K13: =IF(TRIM(Raw_Data!K13)="","Unassigned",PROPER(TRIM(Raw_Data!K13))) -> Faisal Mehmood | L13: =IFERROR(INDEX({"Credit Card","Credit Card","Debit Card","Debit Card","Cash","PayPal"},MATCH(UPPER(LEFT(TRIM(Raw_Data!L13),2)),{"CR","CC","DE","DC","CA","PA"},0)),"Other") -> Credit Card | M13: =IFERROR(INDEX({"Completed","Returned","Cancelled","Pending"},MATCH(UPPER(LEFT(TRIM(Raw_Data!M13),3)),{"COM","RET","CAN","PEN"},0)),"Unknown") -> Completed | N13: =IF(OR(H13="",I13=""),"",H13*I13) -> 1700 | O13: =IF(N13="","",N13*J13) -> 0 | P13: =IF(N13="","",N13-O13) -> 1700 | Q13: =IF(B13="","",DATE(YEAR(B13),MONTH(B13),1)) -> 45901 | R13: =IF(A13="","Invalid - Exclude",IF(COUNTIF($A$2:A13,A13)>1,"Duplicate - Exclude",IF(OR(B13="",H13="",I13=""),"Invalid - Exclude","Valid"))) -> Valid | S13: =IF(R13="Valid","",IF(R13="Duplicate - Exclude","Repeat of an earlier Order ID",IF(B13="","Date missing or unreadable",IF(H13="","Quantity missing or unreadable",IF(I13="","Unit price missing or unreadable","Order ID missing")))))
... A401: =UPPER(TRIM(Raw_Data!A401)) -> ORD-1380 | B401: =IFERROR(IF(ISNUMBER(Raw_Data!B401),Raw_Data!B401,IF(ISNUMBER(FIND("/",Raw_Data!B401)),DATE(VALUE(RIGHT(TRIM(Raw_Data!B401),4)),VALUE(MID(TRIM(Raw_Data!B401),4,2)),VALUE(LEFT(TRIM(Raw_Data!B401),2))),IF(MID(TRIM(Raw_Data!B401),5,1)="-",DATE(VALUE(LEFT(TRIM(Raw_Data!B401),4)),VALUE(MID(TRIM(Raw_Data!B401),6,2)),VALUE(RIGHT(TRIM(Raw_Data!B401),2))),DATE(VALUE(RIGHT(TRIM(Raw_Data!B401),4)),MATCH(MID(TRIM(Raw_Data!B401),4,3),{"Jan","Feb","Mar","Apr","May","Jun","Jul","Aug","Sep","Oct","Nov","Dec"},0),VALUE(LEFT(TRIM(Raw_Data!B401),2)))))),"") -> 45723 | C401: =IF(TRIM(Raw_Data!C401)="","Unknown",PROPER(TRIM(Raw_Data!C401))) -> Unknown | D401: =IFERROR(INDEX({"Punjab","Sindh","KPK","Balochistan"},MATCH(UPPER(LEFT(TRIM(Raw_Data!D401),1)),{"P","S","K","B"},0)),IFERROR(INDEX(Data_Dictionary!$G$4:$G$16,MATCH(E401,Data_Dictionary!$F$4:$F$16,0)),"Unassigned")) -> Punjab | E401: =IF(TRIM(Raw_Data!E401)="","Unknown",PROPER(TRIM(Raw_Data!E401))) -> Multan | F401: =IFERROR(INDEX({"Electronics","Home & Kitchen","Clothing","Groceries","Beauty"},MATCH(UPPER(LEFT(TRIM(Raw_Data!F401),3)),{"ELE","HOM","CLO","GRO","BEA"},0)),"Uncategorised") -> Clothing | G401: =IF(TRIM(Raw_Data!G401)="","Unknown",PROPER(TRIM(Raw_Data!G401))) -> Winter Jacket | H401: =IFERROR(ABS(VALUE(TRIM(Raw_Data!H401))),"") -> 2 | I401: =IFERROR(VALUE(TRIM(SUBSTITUTE(SUBSTITUTE(SUBSTITUTE(SUBSTITUTE(TRIM(Raw_Data!I401),"PKR",""),"Rs.",""),"Rs",""),",",""))),"") -> 10200 | J401: =IFERROR(IF(TRIM(Raw_Data!J401)="",0,IF(VALUE(TRIM(Raw_Data!J401))>1,VALUE(TRIM(Raw_Data!J401))/100,VALUE(TRIM(Raw_Data!J401)))),0) -> 0.1 | K401: =IF(TRIM(Raw_Data!K401)="","Unassigned",PROPER(TRIM(Raw_Data!K401))) -> Zoya Tariq | L401: =IFERROR(INDEX({"Credit Card","Credit Card","Debit Card","Debit Card","Cash","PayPal"},MATCH(UPPER(LEFT(TRIM(Raw_Data!L401),2)),{"CR","CC","DE","DC","CA","PA"},0)),"Other") -> PayPal | M401: =IFERROR(INDEX({"Completed","Returned","Cancelled","Pending"},MATCH(UPPER(LEFT(TRIM(Raw_Data!M401),3)),{"COM","RET","CAN","PEN"},0)),"Unknown") -> Completed | N401: =IF(OR(H401="",I401=""),"",H401*I401) -> 20400 | O401: =IF(N401="","",N401*J401) -> 2040 | P401: =IF(N401="","",N401-O401) -> 18360 | Q401: =IF(B401="","",DATE(YEAR(B401),MONTH(B401),1)) -> 45717 | R401: =IF(A401="","Invalid - Exclude",IF(COUNTIF($A$2:A401,A401)>1,"Duplicate - Exclude",IF(OR(B401="",H401="",I401=""),"Invalid - Exclude","Valid"))) -> Valid | S401: =IF(R401="Valid","",IF(R401="Duplicate - Exclude","Repeat of an earlier Order ID",IF(B401="","Date missing or unreadable",IF(H401="","Quantity missing or unreadable",IF(I401="","Unit price missing or unreadable","Order ID missing")))))

Sheet Data_Dictionary
A1: Data Dictionary - Retail Sales & Regional Performance | F1: Lookup: City to Region
A3: Column | B3: Data Type | C3: Problem in raw data | D3: What I did to clean it | F3: City | G3: Region
A4: Order ID | B4: Text | C4: Mixed upper/lower case, extra spaces, repeated orders | D4: Removed spaces and made upper case (TRIM, UPPER) | F4: Lahore | G4: Punjab
A5: Order Date | B5: Date | C5: 4 different date formats, some blanks | D5: Converted all to one date format using DATE; blanks left empty and flagged | F5: Faisalabad | G5: Punjab
A6: Customer Name | B6: Text | C6: Wrong case, extra spaces, blanks | D6: TRIM and PROPER; blanks set to Unknown | F6: Gujranwala | G6: Punjab
A7: Region | B7: Text | C7: Spelling mistakes, short forms, blanks | D7: Matched to Punjab, Sindh, KPK, Balochistan; blanks filled from City using the lookup table | F7: Multan | G7: Punjab
A8: City | B8: Text | C8: Wrong case, extra spaces, blanks | D8: TRIM and PROPER; blanks set to Unknown | F8: Rawalpindi | G8: Punjab
A9: Category | B9: Text | C9: Typos like Electronic, grocery, Clothes | D9: Matched to 5 standard categories; blanks set to Uncategorised | F9: Karachi | G9: Sindh
A10: Product | B10: Text | C10: Wrong case, extra spaces | D10: TRIM and PROPER | F10: Hyderabad | G10: Sindh
A11: Quantity | B11: Number | C11: Stored as text, negatives, N/A, words, blanks | D11: VALUE and ABS; unreadable values left empty and row flagged | F11: Sukkur | G11: Sindh
A12: Unit Price (PKR) | B12: Number | C12: Rs. and PKR written in the cell, commas, N/A | D12: Removed Rs., PKR and commas with SUBSTITUTE, then VALUE | F12: Peshawar | G12: KPK
A13: Discount % | B13: Percentage | C13: Written as 10%, 0.1 or 10; some blanks | D13: Converted all to a percentage; blank treated as 0% | F13: Mardan | G13: KPK
A14: Sales Rep | B14: Text | C14: Wrong case, extra spaces, blanks | D14: TRIM and PROPER; blanks set to Unassigned | F14: Abbottabad | G14: KPK
... A16: Order Status | B16: Text | C16: Spelling and case differences (canceled, COMPLETE) | D16: Matched to Completed, Returned, Cancelled, Pending | F16: Gwadar | G16: Balochistan
A17: Gross Sales (PKR) | B17: Number | C17: New column | D17: Quantity x Unit Price
A18: Discount Amount (PKR) | B18: Number | C18: New column | D18: Gross Sales x Discount %
A19: Net Revenue (PKR) | B19: Number | C19: New column | D19: Gross Sales - Discount Amount
A20: Order Month | B20: Date | C20: New column | D20: First day of the order month, used for monthly trends
A21: Row Status | B21: Text | C21: New column | D21: Valid, Duplicate - Exclude or Invalid - Exclude
A22: Issue Note | B22: Text | C22: New column | D22: Reason a row was excluded
A25: Cleaning Summary
A26: Total rows in raw data | C26: =COUNTA(Raw_Data!A2:A401) -> 400
A27: Valid rows | C27: =COUNTIF(Clean_Data!R2:R401,"Valid") -> 349
A28: Duplicate rows | C28: =COUNTIF(Clean_Data!R2:R401,"Duplicate*") -> 20
A29: Invalid rows | C29: =COUNTIF(Clean_Data!R2:R401,"Invalid*") -> 31
A30: Blank regions filled from City | C30: =SUMPRODUCT((TRIM(Raw_Data!D2:D401)="")*(Clean_Data!D2:D401<>"Unassigned")) -> 23
A31: Negative quantities corrected | C31: =SUMPRODUCT(--(LEFT(TRIM(Raw_Data!H2:H401),1)="-")) -> 6
A32: Total net revenue of valid rows (PKR) | C32: =SUMIFS(Clean_Data!P2:P401,Clean_Data!R2:R401,"Valid") -> 8688112.5
A35: Assumptions
A36: 1. First time an Order ID appears it is kept, later repeats are marked Duplicate. No rows were deleted.
A37: 2. Negative quantities were treated as typing mistakes and made positive.
A38: 3. Blank discount is treated as 0%.
A39: 4. Rows with unreadable quantity, price or date are marked Invalid and left out of revenue totals.
A40: 5. Returned and Cancelled orders are still in the data, check with the stakeholder if they should be excluded.
A41: 6. All amounts are in PKR. The data is synthetic, made for practice.
